{
  "contents": [
    {
      "title": "Welcome Page",
      "href": "welcome.html"
    },
    {
      "title": "Module 1 - Introduction to Docker",
      "href": "Module_01_Introduction/introduction.html"
    },
    {
      "title": "Module 2 - Docker Fundamentals",
      "href": "Module_02_Fundamentals/fundamentals.html"
    },
    {
      "title": "Module 3 - Docker Architecture & Internals",
      "href": "Module_03_Architecture/architecture.html"
    },
    {
      "title": "Module 4 - Prerequisites",
      "href": "Module_04_Prerequisites/prerequisites.html"
    },
    {
      "title": "Module 5 - Environment Setup",
      "href": "Module_05_Environment_Setup/setup.html"
    },
    {
      "title": "Module 6 - Configuration & daemon.json",
      "href": "Module_06_Configuration/configuration.html"
    },
    {
      "title": "Module 7 - Core Concepts",
      "href": "Module_07_Core_Concepts/core_concepts.html"
    },
    {
      "title": "Module 8 - Deep Dive: Storage, Networks & Drivers",
      "href": "Module_08_Deep_Dive/deep_dive.html"
    },
    {
      "title": "Module 9 - Hands-on Labs",
      "href": "Module_09_Hands-on_Labs/labs.html"
    },
    {
      "title": "Module 10 - Real-World Projects",
      "href": "Module_10_Real_Projects/projects.html"
    },
    {
      "title": "Module 11 - Docker Best Practices",
      "href": "Module_11_Best_Practices/best_practices.html"
    },
    {
      "title": "Module 12 - Container Design Patterns",
      "href": "Module_12_Design_Patterns/design_patterns.html"
    },
    {
      "title": "Module 13 - Docker Security & Hardening",
      "href": "Module_13_Security/security.html"
    },
    {
      "title": "Module 14 - Performance Optimization",
      "href": "Module_14_Performance/performance.html"
    },
    {
      "title": "Module 15 - Debugging & Troubleshooting",
      "href": "Module_15_Debugging/debugging.html"
    },
    {
      "title": "Module 16 - Containerized Testing",
      "href": "Module_16_Testing/testing.html"
    },
    {
      "title": "Module 17 - Deployment & Orchestration",
      "href": "Module_17_Deployment/deployment.html"
    },
    {
      "title": "Module 18 - CI/CD Integration",
      "href": "Module_18_CI_CD/cicd.html"
    },
    {
      "title": "Module 19 - Cloud Integration (AWS)",
      "href": "Module_19_Cloud_Integration/cloud.html"
    },
    {
      "title": "Module 20 - Industry Architecture",
      "href": "Module_20_Industry_Architecture/industry_architecture.html"
    },
    {
      "title": "Module 21 - Common Interview Questions",
      "href": "Module_21_Common_Interview_Questions/interview_questions.html"
    },
    {
      "title": "Module 22 - Cheat Sheets & Reference Guides",
      "href": "Module_22_Cheat_Sheets/cheat_sheets.html"
    },
    {
      "title": "Module 23 - FAQs & Common Confusions",
      "href": "Module_23_FAQs/faqs.html"
    },
    {
      "title": "Module 24 - Capstone Project",
      "href": "Module_24_Capstone_Project/capstone.html"
    },
    {
      "title": "Module 25 - Final Industry Preparation",
      "href": "Module_25_Final_Industry_Preparation/prep.html"
    }
  ]
}